voicelabs/__init__.py
voicelabs/testscript.py
voicelabs/voicelabs.py
voicelabs_assistant-1.0.4.dist-info/DESCRIPTION.rst
voicelabs_assistant-1.0.4.dist-info/METADATA
voicelabs_assistant-1.0.4.dist-info/RECORD
voicelabs_assistant-1.0.4.dist-info/WHEEL
voicelabs_assistant-1.0.4.dist-info/metadata.json
voicelabs_assistant-1.0.4.dist-info/top_level.txt
