Metadata-Version: 2.0
Name: voicelabs-assistant
Version: 1.0.4
Summary: VoiceInsights Python SDK for Google Assistant
Home-page: https://github.com/voicelabs/assistant-python-sdk
Author: VoiceLabs
Author-email: sdk@voicelabs.co
License: MIT
Keywords: voicelabs,voiceinsights,google assistant sdk
Platform: UNKNOWN
Classifier: Intended Audience :: Developers
Classifier: Topic :: Software Development :: Build Tools
Classifier: License :: OSI Approved :: MIT License
Classifier: Programming Language :: Python :: 2.7
Requires-Dist: requests
